melon_top100/__init__.py
melon_top100/melon.py
melon_top100-1.1.0.dist-info/LICENSE
melon_top100-1.1.0.dist-info/METADATA
melon_top100-1.1.0.dist-info/WHEEL
melon_top100-1.1.0.dist-info/top_level.txt
melon_top100-1.1.0.dist-info/RECORD
