Metadata-Version: 2.1
Name: melon-top100
Version: 1.1.0
Summary: This is a package that allows you to easily import Melon Top100 information. Suitable for training lists and dictionaries.
Author-email: Sangkon Han <sigmadream@gmail.com>
Project-URL: Homepage, https://github.com/sigmadream/melon_top100
Project-URL: Bug Tracker, https://github.com/sigmadream/melon_top100/issues
Classifier: Programming Language :: Python :: 3
Classifier: License :: OSI Approved :: MIT License
Classifier: Operating System :: OS Independent
Requires-Python: >=3.8
License-File: LICENSE
Requires-Dist: beautifulsoup4
Requires-Dist: requests
